{
  "$defs": {
    "axiProfile": {
      "description": "AXI profile name: axi3, axi4, or axi4-lite.",
      "enum": [
        "axi3",
        "axi4",
        "axi4-lite"
      ],
      "type": "string"
    },
    "beginRecord": {
      "additionalProperties": true,
      "properties": {
        "$schema": {
          "const": "https://kleverhq.github.io/wavepeek/schema-stream-v2.2.json",
          "type": "string"
        },
        "command": {
          "$ref": "#/$defs/streamCommand"
        },
        "context": {
          "anyOf": [
            {
              "$ref": "#/$defs/streamContextData"
            },
            {
              "type": "null"
            }
          ]
        },
        "seq": {
          "$ref": "#/$defs/sequence"
        },
        "type": {
          "const": "begin"
        }
      },
      "required": [
        "type",
        "seq",
        "command",
        "$schema"
      ],
      "type": "object"
    },
    "canonicalPath": {
      "description": "Canonical dot-separated hierarchy path emitted by wavepeek for a scope or signal.",
      "type": "string"
    },
    "changeItemRecord": {
      "$ref": "#/$defs/itemRecordForChangeSnapshot"
    },
    "changeSignalValue": {
      "additionalProperties": true,
      "properties": {
        "path": {
          "$ref": "#/$defs/canonicalPath",
          "description": "Canonical path of the changed signal."
        },
        "value": {
          "$ref": "#/$defs/sampledValue",
          "description": "Changed signal value at the reported sample point."
        }
      },
      "required": [
        "path",
        "value"
      ],
      "type": "object"
    },
    "changeSnapshot": {
      "additionalProperties": true,
      "properties": {
        "sample_time": {
          "$ref": "#/$defs/normalizedTime",
          "description": "Timestamp used to sample values for this change row."
        },
        "signals": {
          "description": "Changed signal values for this row.",
          "items": {
            "$ref": "#/$defs/changeSignalValue"
          },
          "type": "array"
        },
        "time": {
          "$ref": "#/$defs/normalizedTime",
          "description": "Trigger timestamp emitted by the change command."
        }
      },
      "required": [
        "time",
        "sample_time",
        "signals"
      ],
      "type": "object"
    },
    "diagnostic": {
      "additionalProperties": true,
      "allOf": [
        {
          "if": {
            "properties": {
              "kind": {
                "const": "warning"
              }
            },
            "required": [
              "kind"
            ]
          },
          "then": {
            "properties": {
              "code": {
                "pattern": "^WPK-W[0-9]{4}$"
              }
            },
            "required": [
              "code"
            ]
          }
        },
        {
          "if": {
            "properties": {
              "kind": {
                "const": "error"
              }
            },
            "required": [
              "kind"
            ]
          },
          "then": {
            "properties": {
              "code": {
                "pattern": "^WPK-E[0-9]{4}$"
              }
            },
            "required": [
              "code"
            ]
          }
        },
        {
          "if": {
            "properties": {
              "kind": {
                "const": "info"
              }
            },
            "required": [
              "kind"
            ]
          },
          "then": {
            "not": {
              "required": [
                "code"
              ]
            }
          }
        }
      ],
      "properties": {
        "code": {
          "pattern": "^WPK-[WE][0-9]{4}$",
          "type": "string"
        },
        "kind": {
          "enum": [
            "info",
            "warning",
            "error"
          ],
          "type": "string"
        },
        "message": {
          "type": "string"
        }
      },
      "required": [
        "kind",
        "message"
      ],
      "type": "object"
    },
    "diagnosticRecord": {
      "additionalProperties": true,
      "properties": {
        "command": {
          "$ref": "#/$defs/streamCommand"
        },
        "diagnostic": {
          "$ref": "#/$defs/diagnostic"
        },
        "seq": {
          "$ref": "#/$defs/sequence"
        },
        "type": {
          "const": "diagnostic"
        }
      },
      "required": [
        "type",
        "seq",
        "command",
        "diagnostic"
      ],
      "type": "object"
    },
    "endRecord": {
      "additionalProperties": true,
      "properties": {
        "command": {
          "$ref": "#/$defs/streamCommand"
        },
        "seq": {
          "$ref": "#/$defs/sequence"
        },
        "summary": {
          "$ref": "#/$defs/streamSummary"
        },
        "type": {
          "const": "end"
        }
      },
      "required": [
        "type",
        "seq",
        "command",
        "summary"
      ],
      "type": "object"
    },
    "extractAxi3ArTransfer": {
      "additionalProperties": true,
      "properties": {
        "channel": {
          "const": "ar",
          "description": "AXI ready/valid channel name."
        },
        "payload": {
          "additionalProperties": false,
          "description": "Payload values keyed by lowercase AXI standard signal name. Keys are optional because extraction emits only mapped payload signals.",
          "properties": {
            "araddr": {
              "$ref": "#/$defs/sampledValue"
            },
            "arburst": {
              "$ref": "#/$defs/sampledValue"
            },
            "arcache": {
              "$ref": "#/$defs/sampledValue"
            },
            "arid": {
              "$ref": "#/$defs/sampledValue"
            },
            "arlen": {
              "$ref": "#/$defs/sampledValue"
            },
            "arlock": {
              "$ref": "#/$defs/sampledValue"
            },
            "arprot": {
              "$ref": "#/$defs/sampledValue"
            },
            "arsize": {
              "$ref": "#/$defs/sampledValue"
            }
          },
          "type": "object"
        },
        "profile": {
          "const": "axi3",
          "description": "AXI profile name for this transfer row."
        },
        "sample_time": {
          "$ref": "#/$defs/normalizedTime",
          "description": "Pre-edge timestamp used to evaluate ready/valid and sample payload values."
        },
        "time": {
          "$ref": "#/$defs/normalizedTime",
          "description": "Selected AXI transfer event timestamp."
        }
      },
      "required": [
        "time",
        "sample_time",
        "profile",
        "channel",
        "payload"
      ],
      "type": "object"
    },
    "extractAxi3AwTransfer": {
      "additionalProperties": true,
      "properties": {
        "channel": {
          "const": "aw",
          "description": "AXI ready/valid channel name."
        },
        "payload": {
          "additionalProperties": false,
          "description": "Payload values keyed by lowercase AXI standard signal name. Keys are optional because extraction emits only mapped payload signals.",
          "properties": {
            "awaddr": {
              "$ref": "#/$defs/sampledValue"
            },
            "awburst": {
              "$ref": "#/$defs/sampledValue"
            },
            "awcache": {
              "$ref": "#/$defs/sampledValue"
            },
            "awid": {
              "$ref": "#/$defs/sampledValue"
            },
            "awlen": {
              "$ref": "#/$defs/sampledValue"
            },
            "awlock": {
              "$ref": "#/$defs/sampledValue"
            },
            "awprot": {
              "$ref": "#/$defs/sampledValue"
            },
            "awsize": {
              "$ref": "#/$defs/sampledValue"
            }
          },
          "type": "object"
        },
        "profile": {
          "const": "axi3",
          "description": "AXI profile name for this transfer row."
        },
        "sample_time": {
          "$ref": "#/$defs/normalizedTime",
          "description": "Pre-edge timestamp used to evaluate ready/valid and sample payload values."
        },
        "time": {
          "$ref": "#/$defs/normalizedTime",
          "description": "Selected AXI transfer event timestamp."
        }
      },
      "required": [
        "time",
        "sample_time",
        "profile",
        "channel",
        "payload"
      ],
      "type": "object"
    },
    "extractAxi3BTransfer": {
      "additionalProperties": true,
      "properties": {
        "channel": {
          "const": "b",
          "description": "AXI ready/valid channel name."
        },
        "payload": {
          "additionalProperties": false,
          "description": "Payload values keyed by lowercase AXI standard signal name. Keys are optional because extraction emits only mapped payload signals.",
          "properties": {
            "bid": {
              "$ref": "#/$defs/sampledValue"
            },
            "bresp": {
              "$ref": "#/$defs/sampledValue"
            }
          },
          "type": "object"
        },
        "profile": {
          "const": "axi3",
          "description": "AXI profile name for this transfer row."
        },
        "sample_time": {
          "$ref": "#/$defs/normalizedTime",
          "description": "Pre-edge timestamp used to evaluate ready/valid and sample payload values."
        },
        "time": {
          "$ref": "#/$defs/normalizedTime",
          "description": "Selected AXI transfer event timestamp."
        }
      },
      "required": [
        "time",
        "sample_time",
        "profile",
        "channel",
        "payload"
      ],
      "type": "object"
    },
    "extractAxi3RTransfer": {
      "additionalProperties": true,
      "properties": {
        "channel": {
          "const": "r",
          "description": "AXI ready/valid channel name."
        },
        "payload": {
          "additionalProperties": false,
          "description": "Payload values keyed by lowercase AXI standard signal name. Keys are optional because extraction emits only mapped payload signals.",
          "properties": {
            "rdata": {
              "$ref": "#/$defs/sampledValue"
            },
            "rid": {
              "$ref": "#/$defs/sampledValue"
            },
            "rlast": {
              "$ref": "#/$defs/sampledValue"
            },
            "rresp": {
              "$ref": "#/$defs/sampledValue"
            }
          },
          "type": "object"
        },
        "profile": {
          "const": "axi3",
          "description": "AXI profile name for this transfer row."
        },
        "sample_time": {
          "$ref": "#/$defs/normalizedTime",
          "description": "Pre-edge timestamp used to evaluate ready/valid and sample payload values."
        },
        "time": {
          "$ref": "#/$defs/normalizedTime",
          "description": "Selected AXI transfer event timestamp."
        }
      },
      "required": [
        "time",
        "sample_time",
        "profile",
        "channel",
        "payload"
      ],
      "type": "object"
    },
    "extractAxi3Transfer": {
      "oneOf": [
        {
          "$ref": "#/$defs/extractAxi3AwTransfer"
        },
        {
          "$ref": "#/$defs/extractAxi3WTransfer"
        },
        {
          "$ref": "#/$defs/extractAxi3BTransfer"
        },
        {
          "$ref": "#/$defs/extractAxi3ArTransfer"
        },
        {
          "$ref": "#/$defs/extractAxi3RTransfer"
        }
      ]
    },
    "extractAxi3WTransfer": {
      "additionalProperties": true,
      "properties": {
        "channel": {
          "const": "w",
          "description": "AXI ready/valid channel name."
        },
        "payload": {
          "additionalProperties": false,
          "description": "Payload values keyed by lowercase AXI standard signal name. Keys are optional because extraction emits only mapped payload signals.",
          "properties": {
            "wdata": {
              "$ref": "#/$defs/sampledValue"
            },
            "wid": {
              "$ref": "#/$defs/sampledValue"
            },
            "wlast": {
              "$ref": "#/$defs/sampledValue"
            },
            "wstrb": {
              "$ref": "#/$defs/sampledValue"
            }
          },
          "type": "object"
        },
        "profile": {
          "const": "axi3",
          "description": "AXI profile name for this transfer row."
        },
        "sample_time": {
          "$ref": "#/$defs/normalizedTime",
          "description": "Pre-edge timestamp used to evaluate ready/valid and sample payload values."
        },
        "time": {
          "$ref": "#/$defs/normalizedTime",
          "description": "Selected AXI transfer event timestamp."
        }
      },
      "required": [
        "time",
        "sample_time",
        "profile",
        "channel",
        "payload"
      ],
      "type": "object"
    },
    "extractAxi4ArTransfer": {
      "additionalProperties": true,
      "properties": {
        "channel": {
          "const": "ar",
          "description": "AXI ready/valid channel name."
        },
        "payload": {
          "additionalProperties": false,
          "description": "Payload values keyed by lowercase AXI standard signal name. Keys are optional because extraction emits only mapped payload signals.",
          "properties": {
            "araddr": {
              "$ref": "#/$defs/sampledValue"
            },
            "arburst": {
              "$ref": "#/$defs/sampledValue"
            },
            "arcache": {
              "$ref": "#/$defs/sampledValue"
            },
            "arid": {
              "$ref": "#/$defs/sampledValue"
            },
            "arlen": {
              "$ref": "#/$defs/sampledValue"
            },
            "arlock": {
              "$ref": "#/$defs/sampledValue"
            },
            "arprot": {
              "$ref": "#/$defs/sampledValue"
            },
            "arqos": {
              "$ref": "#/$defs/sampledValue"
            },
            "arregion": {
              "$ref": "#/$defs/sampledValue"
            },
            "arsize": {
              "$ref": "#/$defs/sampledValue"
            },
            "aruser": {
              "$ref": "#/$defs/sampledValue"
            }
          },
          "type": "object"
        },
        "profile": {
          "const": "axi4",
          "description": "AXI profile name for this transfer row."
        },
        "sample_time": {
          "$ref": "#/$defs/normalizedTime",
          "description": "Pre-edge timestamp used to evaluate ready/valid and sample payload values."
        },
        "time": {
          "$ref": "#/$defs/normalizedTime",
          "description": "Selected AXI transfer event timestamp."
        }
      },
      "required": [
        "time",
        "sample_time",
        "profile",
        "channel",
        "payload"
      ],
      "type": "object"
    },
    "extractAxi4AwTransfer": {
      "additionalProperties": true,
      "properties": {
        "channel": {
          "const": "aw",
          "description": "AXI ready/valid channel name."
        },
        "payload": {
          "additionalProperties": false,
          "description": "Payload values keyed by lowercase AXI standard signal name. Keys are optional because extraction emits only mapped payload signals.",
          "properties": {
            "awaddr": {
              "$ref": "#/$defs/sampledValue"
            },
            "awburst": {
              "$ref": "#/$defs/sampledValue"
            },
            "awcache": {
              "$ref": "#/$defs/sampledValue"
            },
            "awid": {
              "$ref": "#/$defs/sampledValue"
            },
            "awlen": {
              "$ref": "#/$defs/sampledValue"
            },
            "awlock": {
              "$ref": "#/$defs/sampledValue"
            },
            "awprot": {
              "$ref": "#/$defs/sampledValue"
            },
            "awqos": {
              "$ref": "#/$defs/sampledValue"
            },
            "awregion": {
              "$ref": "#/$defs/sampledValue"
            },
            "awsize": {
              "$ref": "#/$defs/sampledValue"
            },
            "awuser": {
              "$ref": "#/$defs/sampledValue"
            }
          },
          "type": "object"
        },
        "profile": {
          "const": "axi4",
          "description": "AXI profile name for this transfer row."
        },
        "sample_time": {
          "$ref": "#/$defs/normalizedTime",
          "description": "Pre-edge timestamp used to evaluate ready/valid and sample payload values."
        },
        "time": {
          "$ref": "#/$defs/normalizedTime",
          "description": "Selected AXI transfer event timestamp."
        }
      },
      "required": [
        "time",
        "sample_time",
        "profile",
        "channel",
        "payload"
      ],
      "type": "object"
    },
    "extractAxi4BTransfer": {
      "additionalProperties": true,
      "properties": {
        "channel": {
          "const": "b",
          "description": "AXI ready/valid channel name."
        },
        "payload": {
          "additionalProperties": false,
          "description": "Payload values keyed by lowercase AXI standard signal name. Keys are optional because extraction emits only mapped payload signals.",
          "properties": {
            "bid": {
              "$ref": "#/$defs/sampledValue"
            },
            "bresp": {
              "$ref": "#/$defs/sampledValue"
            },
            "buser": {
              "$ref": "#/$defs/sampledValue"
            }
          },
          "type": "object"
        },
        "profile": {
          "const": "axi4",
          "description": "AXI profile name for this transfer row."
        },
        "sample_time": {
          "$ref": "#/$defs/normalizedTime",
          "description": "Pre-edge timestamp used to evaluate ready/valid and sample payload values."
        },
        "time": {
          "$ref": "#/$defs/normalizedTime",
          "description": "Selected AXI transfer event timestamp."
        }
      },
      "required": [
        "time",
        "sample_time",
        "profile",
        "channel",
        "payload"
      ],
      "type": "object"
    },
    "extractAxi4LiteArTransfer": {
      "additionalProperties": true,
      "properties": {
        "channel": {
          "const": "ar",
          "description": "AXI ready/valid channel name."
        },
        "payload": {
          "additionalProperties": false,
          "description": "Payload values keyed by lowercase AXI standard signal name. Keys are optional because extraction emits only mapped payload signals.",
          "properties": {
            "araddr": {
              "$ref": "#/$defs/sampledValue"
            },
            "arprot": {
              "$ref": "#/$defs/sampledValue"
            }
          },
          "type": "object"
        },
        "profile": {
          "const": "axi4-lite",
          "description": "AXI profile name for this transfer row."
        },
        "sample_time": {
          "$ref": "#/$defs/normalizedTime",
          "description": "Pre-edge timestamp used to evaluate ready/valid and sample payload values."
        },
        "time": {
          "$ref": "#/$defs/normalizedTime",
          "description": "Selected AXI transfer event timestamp."
        }
      },
      "required": [
        "time",
        "sample_time",
        "profile",
        "channel",
        "payload"
      ],
      "type": "object"
    },
    "extractAxi4LiteAwTransfer": {
      "additionalProperties": true,
      "properties": {
        "channel": {
          "const": "aw",
          "description": "AXI ready/valid channel name."
        },
        "payload": {
          "additionalProperties": false,
          "description": "Payload values keyed by lowercase AXI standard signal name. Keys are optional because extraction emits only mapped payload signals.",
          "properties": {
            "awaddr": {
              "$ref": "#/$defs/sampledValue"
            },
            "awprot": {
              "$ref": "#/$defs/sampledValue"
            }
          },
          "type": "object"
        },
        "profile": {
          "const": "axi4-lite",
          "description": "AXI profile name for this transfer row."
        },
        "sample_time": {
          "$ref": "#/$defs/normalizedTime",
          "description": "Pre-edge timestamp used to evaluate ready/valid and sample payload values."
        },
        "time": {
          "$ref": "#/$defs/normalizedTime",
          "description": "Selected AXI transfer event timestamp."
        }
      },
      "required": [
        "time",
        "sample_time",
        "profile",
        "channel",
        "payload"
      ],
      "type": "object"
    },
    "extractAxi4LiteBTransfer": {
      "additionalProperties": true,
      "properties": {
        "channel": {
          "const": "b",
          "description": "AXI ready/valid channel name."
        },
        "payload": {
          "additionalProperties": false,
          "description": "Payload values keyed by lowercase AXI standard signal name. Keys are optional because extraction emits only mapped payload signals.",
          "properties": {
            "bresp": {
              "$ref": "#/$defs/sampledValue"
            }
          },
          "type": "object"
        },
        "profile": {
          "const": "axi4-lite",
          "description": "AXI profile name for this transfer row."
        },
        "sample_time": {
          "$ref": "#/$defs/normalizedTime",
          "description": "Pre-edge timestamp used to evaluate ready/valid and sample payload values."
        },
        "time": {
          "$ref": "#/$defs/normalizedTime",
          "description": "Selected AXI transfer event timestamp."
        }
      },
      "required": [
        "time",
        "sample_time",
        "profile",
        "channel",
        "payload"
      ],
      "type": "object"
    },
    "extractAxi4LiteRTransfer": {
      "additionalProperties": true,
      "properties": {
        "channel": {
          "const": "r",
          "description": "AXI ready/valid channel name."
        },
        "payload": {
          "additionalProperties": false,
          "description": "Payload values keyed by lowercase AXI standard signal name. Keys are optional because extraction emits only mapped payload signals.",
          "properties": {
            "rdata": {
              "$ref": "#/$defs/sampledValue"
            },
            "rresp": {
              "$ref": "#/$defs/sampledValue"
            }
          },
          "type": "object"
        },
        "profile": {
          "const": "axi4-lite",
          "description": "AXI profile name for this transfer row."
        },
        "sample_time": {
          "$ref": "#/$defs/normalizedTime",
          "description": "Pre-edge timestamp used to evaluate ready/valid and sample payload values."
        },
        "time": {
          "$ref": "#/$defs/normalizedTime",
          "description": "Selected AXI transfer event timestamp."
        }
      },
      "required": [
        "time",
        "sample_time",
        "profile",
        "channel",
        "payload"
      ],
      "type": "object"
    },
    "extractAxi4LiteTransfer": {
      "oneOf": [
        {
          "$ref": "#/$defs/extractAxi4LiteAwTransfer"
        },
        {
          "$ref": "#/$defs/extractAxi4LiteWTransfer"
        },
        {
          "$ref": "#/$defs/extractAxi4LiteBTransfer"
        },
        {
          "$ref": "#/$defs/extractAxi4LiteArTransfer"
        },
        {
          "$ref": "#/$defs/extractAxi4LiteRTransfer"
        }
      ]
    },
    "extractAxi4LiteWTransfer": {
      "additionalProperties": true,
      "properties": {
        "channel": {
          "const": "w",
          "description": "AXI ready/valid channel name."
        },
        "payload": {
          "additionalProperties": false,
          "description": "Payload values keyed by lowercase AXI standard signal name. Keys are optional because extraction emits only mapped payload signals.",
          "properties": {
            "wdata": {
              "$ref": "#/$defs/sampledValue"
            },
            "wstrb": {
              "$ref": "#/$defs/sampledValue"
            }
          },
          "type": "object"
        },
        "profile": {
          "const": "axi4-lite",
          "description": "AXI profile name for this transfer row."
        },
        "sample_time": {
          "$ref": "#/$defs/normalizedTime",
          "description": "Pre-edge timestamp used to evaluate ready/valid and sample payload values."
        },
        "time": {
          "$ref": "#/$defs/normalizedTime",
          "description": "Selected AXI transfer event timestamp."
        }
      },
      "required": [
        "time",
        "sample_time",
        "profile",
        "channel",
        "payload"
      ],
      "type": "object"
    },
    "extractAxi4RTransfer": {
      "additionalProperties": true,
      "properties": {
        "channel": {
          "const": "r",
          "description": "AXI ready/valid channel name."
        },
        "payload": {
          "additionalProperties": false,
          "description": "Payload values keyed by lowercase AXI standard signal name. Keys are optional because extraction emits only mapped payload signals.",
          "properties": {
            "rdata": {
              "$ref": "#/$defs/sampledValue"
            },
            "rid": {
              "$ref": "#/$defs/sampledValue"
            },
            "rlast": {
              "$ref": "#/$defs/sampledValue"
            },
            "rresp": {
              "$ref": "#/$defs/sampledValue"
            },
            "ruser": {
              "$ref": "#/$defs/sampledValue"
            }
          },
          "type": "object"
        },
        "profile": {
          "const": "axi4",
          "description": "AXI profile name for this transfer row."
        },
        "sample_time": {
          "$ref": "#/$defs/normalizedTime",
          "description": "Pre-edge timestamp used to evaluate ready/valid and sample payload values."
        },
        "time": {
          "$ref": "#/$defs/normalizedTime",
          "description": "Selected AXI transfer event timestamp."
        }
      },
      "required": [
        "time",
        "sample_time",
        "profile",
        "channel",
        "payload"
      ],
      "type": "object"
    },
    "extractAxi4Transfer": {
      "oneOf": [
        {
          "$ref": "#/$defs/extractAxi4AwTransfer"
        },
        {
          "$ref": "#/$defs/extractAxi4WTransfer"
        },
        {
          "$ref": "#/$defs/extractAxi4BTransfer"
        },
        {
          "$ref": "#/$defs/extractAxi4ArTransfer"
        },
        {
          "$ref": "#/$defs/extractAxi4RTransfer"
        }
      ]
    },
    "extractAxi4WTransfer": {
      "additionalProperties": true,
      "properties": {
        "channel": {
          "const": "w",
          "description": "AXI ready/valid channel name."
        },
        "payload": {
          "additionalProperties": false,
          "description": "Payload values keyed by lowercase AXI standard signal name. Keys are optional because extraction emits only mapped payload signals.",
          "properties": {
            "wdata": {
              "$ref": "#/$defs/sampledValue"
            },
            "wlast": {
              "$ref": "#/$defs/sampledValue"
            },
            "wstrb": {
              "$ref": "#/$defs/sampledValue"
            },
            "wuser": {
              "$ref": "#/$defs/sampledValue"
            }
          },
          "type": "object"
        },
        "profile": {
          "const": "axi4",
          "description": "AXI profile name for this transfer row."
        },
        "sample_time": {
          "$ref": "#/$defs/normalizedTime",
          "description": "Pre-edge timestamp used to evaluate ready/valid and sample payload values."
        },
        "time": {
          "$ref": "#/$defs/normalizedTime",
          "description": "Selected AXI transfer event timestamp."
        }
      },
      "required": [
        "time",
        "sample_time",
        "profile",
        "channel",
        "payload"
      ],
      "type": "object"
    },
    "extractAxiContext": {
      "oneOf": [
        {
          "additionalProperties": true,
          "properties": {
            "issue": {
              "const": "H.c",
              "description": "Arm IHI 0022 issue used for this profile definition."
            },
            "mappings": {
              "additionalProperties": false,
              "description": "Resolved waveform mappings keyed by lowercase AXI standard signal name.",
              "properties": {
                "aclk": {
                  "$ref": "#/$defs/extractAxiMapping"
                },
                "araddr": {
                  "$ref": "#/$defs/extractAxiMapping"
                },
                "arburst": {
                  "$ref": "#/$defs/extractAxiMapping"
                },
                "arcache": {
                  "$ref": "#/$defs/extractAxiMapping"
                },
                "aresetn": {
                  "$ref": "#/$defs/extractAxiMapping"
                },
                "arid": {
                  "$ref": "#/$defs/extractAxiMapping"
                },
                "arlen": {
                  "$ref": "#/$defs/extractAxiMapping"
                },
                "arlock": {
                  "$ref": "#/$defs/extractAxiMapping"
                },
                "arprot": {
                  "$ref": "#/$defs/extractAxiMapping"
                },
                "arready": {
                  "$ref": "#/$defs/extractAxiMapping"
                },
                "arsize": {
                  "$ref": "#/$defs/extractAxiMapping"
                },
                "arvalid": {
                  "$ref": "#/$defs/extractAxiMapping"
                },
                "awaddr": {
                  "$ref": "#/$defs/extractAxiMapping"
                },
                "awburst": {
                  "$ref": "#/$defs/extractAxiMapping"
                },
                "awcache": {
                  "$ref": "#/$defs/extractAxiMapping"
                },
                "awid": {
                  "$ref": "#/$defs/extractAxiMapping"
                },
                "awlen": {
                  "$ref": "#/$defs/extractAxiMapping"
                },
                "awlock": {
                  "$ref": "#/$defs/extractAxiMapping"
                },
                "awprot": {
                  "$ref": "#/$defs/extractAxiMapping"
                },
                "awready": {
                  "$ref": "#/$defs/extractAxiMapping"
                },
                "awsize": {
                  "$ref": "#/$defs/extractAxiMapping"
                },
                "awvalid": {
                  "$ref": "#/$defs/extractAxiMapping"
                },
                "bid": {
                  "$ref": "#/$defs/extractAxiMapping"
                },
                "bready": {
                  "$ref": "#/$defs/extractAxiMapping"
                },
                "bresp": {
                  "$ref": "#/$defs/extractAxiMapping"
                },
                "bvalid": {
                  "$ref": "#/$defs/extractAxiMapping"
                },
                "rdata": {
                  "$ref": "#/$defs/extractAxiMapping"
                },
                "rid": {
                  "$ref": "#/$defs/extractAxiMapping"
                },
                "rlast": {
                  "$ref": "#/$defs/extractAxiMapping"
                },
                "rready": {
                  "$ref": "#/$defs/extractAxiMapping"
                },
                "rresp": {
                  "$ref": "#/$defs/extractAxiMapping"
                },
                "rvalid": {
                  "$ref": "#/$defs/extractAxiMapping"
                },
                "wdata": {
                  "$ref": "#/$defs/extractAxiMapping"
                },
                "wid": {
                  "$ref": "#/$defs/extractAxiMapping"
                },
                "wlast": {
                  "$ref": "#/$defs/extractAxiMapping"
                },
                "wready": {
                  "$ref": "#/$defs/extractAxiMapping"
                },
                "wstrb": {
                  "$ref": "#/$defs/extractAxiMapping"
                },
                "wvalid": {
                  "$ref": "#/$defs/extractAxiMapping"
                }
              },
              "type": "object"
            },
            "name": {
              "description": "AXI port name supplied by CLI or source JSON.",
              "type": "string"
            },
            "profile": {
              "const": "axi3",
              "description": "AXI profile name used for standard signal mapping."
            }
          },
          "required": [
            "name",
            "profile",
            "issue",
            "mappings"
          ],
          "type": "object"
        },
        {
          "additionalProperties": true,
          "properties": {
            "issue": {
              "const": "H.c",
              "description": "Arm IHI 0022 issue used for this profile definition."
            },
            "mappings": {
              "additionalProperties": false,
              "description": "Resolved waveform mappings keyed by lowercase AXI standard signal name.",
              "properties": {
                "aclk": {
                  "$ref": "#/$defs/extractAxiMapping"
                },
                "araddr": {
                  "$ref": "#/$defs/extractAxiMapping"
                },
                "arburst": {
                  "$ref": "#/$defs/extractAxiMapping"
                },
                "arcache": {
                  "$ref": "#/$defs/extractAxiMapping"
                },
                "aresetn": {
                  "$ref": "#/$defs/extractAxiMapping"
                },
                "arid": {
                  "$ref": "#/$defs/extractAxiMapping"
                },
                "arlen": {
                  "$ref": "#/$defs/extractAxiMapping"
                },
                "arlock": {
                  "$ref": "#/$defs/extractAxiMapping"
                },
                "arprot": {
                  "$ref": "#/$defs/extractAxiMapping"
                },
                "arqos": {
                  "$ref": "#/$defs/extractAxiMapping"
                },
                "arready": {
                  "$ref": "#/$defs/extractAxiMapping"
                },
                "arregion": {
                  "$ref": "#/$defs/extractAxiMapping"
                },
                "arsize": {
                  "$ref": "#/$defs/extractAxiMapping"
                },
                "aruser": {
                  "$ref": "#/$defs/extractAxiMapping"
                },
                "arvalid": {
                  "$ref": "#/$defs/extractAxiMapping"
                },
                "awaddr": {
                  "$ref": "#/$defs/extractAxiMapping"
                },
                "awburst": {
                  "$ref": "#/$defs/extractAxiMapping"
                },
                "awcache": {
                  "$ref": "#/$defs/extractAxiMapping"
                },
                "awid": {
                  "$ref": "#/$defs/extractAxiMapping"
                },
                "awlen": {
                  "$ref": "#/$defs/extractAxiMapping"
                },
                "awlock": {
                  "$ref": "#/$defs/extractAxiMapping"
                },
                "awprot": {
                  "$ref": "#/$defs/extractAxiMapping"
                },
                "awqos": {
                  "$ref": "#/$defs/extractAxiMapping"
                },
                "awready": {
                  "$ref": "#/$defs/extractAxiMapping"
                },
                "awregion": {
                  "$ref": "#/$defs/extractAxiMapping"
                },
                "awsize": {
                  "$ref": "#/$defs/extractAxiMapping"
                },
                "awuser": {
                  "$ref": "#/$defs/extractAxiMapping"
                },
                "awvalid": {
                  "$ref": "#/$defs/extractAxiMapping"
                },
                "bid": {
                  "$ref": "#/$defs/extractAxiMapping"
                },
                "bready": {
                  "$ref": "#/$defs/extractAxiMapping"
                },
                "bresp": {
                  "$ref": "#/$defs/extractAxiMapping"
                },
                "buser": {
                  "$ref": "#/$defs/extractAxiMapping"
                },
                "bvalid": {
                  "$ref": "#/$defs/extractAxiMapping"
                },
                "rdata": {
                  "$ref": "#/$defs/extractAxiMapping"
                },
                "rid": {
                  "$ref": "#/$defs/extractAxiMapping"
                },
                "rlast": {
                  "$ref": "#/$defs/extractAxiMapping"
                },
                "rready": {
                  "$ref": "#/$defs/extractAxiMapping"
                },
                "rresp": {
                  "$ref": "#/$defs/extractAxiMapping"
                },
                "ruser": {
                  "$ref": "#/$defs/extractAxiMapping"
                },
                "rvalid": {
                  "$ref": "#/$defs/extractAxiMapping"
                },
                "wdata": {
                  "$ref": "#/$defs/extractAxiMapping"
                },
                "wlast": {
                  "$ref": "#/$defs/extractAxiMapping"
                },
                "wready": {
                  "$ref": "#/$defs/extractAxiMapping"
                },
                "wstrb": {
                  "$ref": "#/$defs/extractAxiMapping"
                },
                "wuser": {
                  "$ref": "#/$defs/extractAxiMapping"
                },
                "wvalid": {
                  "$ref": "#/$defs/extractAxiMapping"
                }
              },
              "type": "object"
            },
            "name": {
              "description": "AXI port name supplied by CLI or source JSON.",
              "type": "string"
            },
            "profile": {
              "const": "axi4",
              "description": "AXI profile name used for standard signal mapping."
            }
          },
          "required": [
            "name",
            "profile",
            "issue",
            "mappings"
          ],
          "type": "object"
        },
        {
          "additionalProperties": true,
          "properties": {
            "issue": {
              "const": "H.c",
              "description": "Arm IHI 0022 issue used for this profile definition."
            },
            "mappings": {
              "additionalProperties": false,
              "description": "Resolved waveform mappings keyed by lowercase AXI standard signal name.",
              "properties": {
                "aclk": {
                  "$ref": "#/$defs/extractAxiMapping"
                },
                "araddr": {
                  "$ref": "#/$defs/extractAxiMapping"
                },
                "aresetn": {
                  "$ref": "#/$defs/extractAxiMapping"
                },
                "arprot": {
                  "$ref": "#/$defs/extractAxiMapping"
                },
                "arready": {
                  "$ref": "#/$defs/extractAxiMapping"
                },
                "arvalid": {
                  "$ref": "#/$defs/extractAxiMapping"
                },
                "awaddr": {
                  "$ref": "#/$defs/extractAxiMapping"
                },
                "awprot": {
                  "$ref": "#/$defs/extractAxiMapping"
                },
                "awready": {
                  "$ref": "#/$defs/extractAxiMapping"
                },
                "awvalid": {
                  "$ref": "#/$defs/extractAxiMapping"
                },
                "bready": {
                  "$ref": "#/$defs/extractAxiMapping"
                },
                "bresp": {
                  "$ref": "#/$defs/extractAxiMapping"
                },
                "bvalid": {
                  "$ref": "#/$defs/extractAxiMapping"
                },
                "rdata": {
                  "$ref": "#/$defs/extractAxiMapping"
                },
                "rready": {
                  "$ref": "#/$defs/extractAxiMapping"
                },
                "rresp": {
                  "$ref": "#/$defs/extractAxiMapping"
                },
                "rvalid": {
                  "$ref": "#/$defs/extractAxiMapping"
                },
                "wdata": {
                  "$ref": "#/$defs/extractAxiMapping"
                },
                "wready": {
                  "$ref": "#/$defs/extractAxiMapping"
                },
                "wstrb": {
                  "$ref": "#/$defs/extractAxiMapping"
                },
                "wvalid": {
                  "$ref": "#/$defs/extractAxiMapping"
                }
              },
              "type": "object"
            },
            "name": {
              "description": "AXI port name supplied by CLI or source JSON.",
              "type": "string"
            },
            "profile": {
              "const": "axi4-lite",
              "description": "AXI profile name used for standard signal mapping."
            }
          },
          "required": [
            "name",
            "profile",
            "issue",
            "mappings"
          ],
          "type": "object"
        }
      ]
    },
    "extractAxiData": {
      "oneOf": [
        {
          "additionalProperties": true,
          "properties": {
            "issue": {
              "const": "H.c",
              "description": "Arm IHI 0022 issue used for this profile definition."
            },
            "mappings": {
              "additionalProperties": false,
              "description": "Resolved waveform mappings keyed by lowercase AXI standard signal name.",
              "properties": {
                "aclk": {
                  "$ref": "#/$defs/extractAxiMapping"
                },
                "araddr": {
                  "$ref": "#/$defs/extractAxiMapping"
                },
                "arburst": {
                  "$ref": "#/$defs/extractAxiMapping"
                },
                "arcache": {
                  "$ref": "#/$defs/extractAxiMapping"
                },
                "aresetn": {
                  "$ref": "#/$defs/extractAxiMapping"
                },
                "arid": {
                  "$ref": "#/$defs/extractAxiMapping"
                },
                "arlen": {
                  "$ref": "#/$defs/extractAxiMapping"
                },
                "arlock": {
                  "$ref": "#/$defs/extractAxiMapping"
                },
                "arprot": {
                  "$ref": "#/$defs/extractAxiMapping"
                },
                "arready": {
                  "$ref": "#/$defs/extractAxiMapping"
                },
                "arsize": {
                  "$ref": "#/$defs/extractAxiMapping"
                },
                "arvalid": {
                  "$ref": "#/$defs/extractAxiMapping"
                },
                "awaddr": {
                  "$ref": "#/$defs/extractAxiMapping"
                },
                "awburst": {
                  "$ref": "#/$defs/extractAxiMapping"
                },
                "awcache": {
                  "$ref": "#/$defs/extractAxiMapping"
                },
                "awid": {
                  "$ref": "#/$defs/extractAxiMapping"
                },
                "awlen": {
                  "$ref": "#/$defs/extractAxiMapping"
                },
                "awlock": {
                  "$ref": "#/$defs/extractAxiMapping"
                },
                "awprot": {
                  "$ref": "#/$defs/extractAxiMapping"
                },
                "awready": {
                  "$ref": "#/$defs/extractAxiMapping"
                },
                "awsize": {
                  "$ref": "#/$defs/extractAxiMapping"
                },
                "awvalid": {
                  "$ref": "#/$defs/extractAxiMapping"
                },
                "bid": {
                  "$ref": "#/$defs/extractAxiMapping"
                },
                "bready": {
                  "$ref": "#/$defs/extractAxiMapping"
                },
                "bresp": {
                  "$ref": "#/$defs/extractAxiMapping"
                },
                "bvalid": {
                  "$ref": "#/$defs/extractAxiMapping"
                },
                "rdata": {
                  "$ref": "#/$defs/extractAxiMapping"
                },
                "rid": {
                  "$ref": "#/$defs/extractAxiMapping"
                },
                "rlast": {
                  "$ref": "#/$defs/extractAxiMapping"
                },
                "rready": {
                  "$ref": "#/$defs/extractAxiMapping"
                },
                "rresp": {
                  "$ref": "#/$defs/extractAxiMapping"
                },
                "rvalid": {
                  "$ref": "#/$defs/extractAxiMapping"
                },
                "wdata": {
                  "$ref": "#/$defs/extractAxiMapping"
                },
                "wid": {
                  "$ref": "#/$defs/extractAxiMapping"
                },
                "wlast": {
                  "$ref": "#/$defs/extractAxiMapping"
                },
                "wready": {
                  "$ref": "#/$defs/extractAxiMapping"
                },
                "wstrb": {
                  "$ref": "#/$defs/extractAxiMapping"
                },
                "wvalid": {
                  "$ref": "#/$defs/extractAxiMapping"
                }
              },
              "type": "object"
            },
            "name": {
              "description": "AXI port name supplied by CLI or source JSON.",
              "type": "string"
            },
            "profile": {
              "const": "axi3",
              "description": "AXI profile name used for standard signal mapping."
            },
            "transfers": {
              "description": "Extracted AXI ready/valid transfers in event order.",
              "items": {
                "$ref": "#/$defs/extractAxi3Transfer"
              },
              "type": "array"
            }
          },
          "required": [
            "name",
            "profile",
            "issue",
            "mappings",
            "transfers"
          ],
          "type": "object"
        },
        {
          "additionalProperties": true,
          "properties": {
            "issue": {
              "const": "H.c",
              "description": "Arm IHI 0022 issue used for this profile definition."
            },
            "mappings": {
              "additionalProperties": false,
              "description": "Resolved waveform mappings keyed by lowercase AXI standard signal name.",
              "properties": {
                "aclk": {
                  "$ref": "#/$defs/extractAxiMapping"
                },
                "araddr": {
                  "$ref": "#/$defs/extractAxiMapping"
                },
                "arburst": {
                  "$ref": "#/$defs/extractAxiMapping"
                },
                "arcache": {
                  "$ref": "#/$defs/extractAxiMapping"
                },
                "aresetn": {
                  "$ref": "#/$defs/extractAxiMapping"
                },
                "arid": {
                  "$ref": "#/$defs/extractAxiMapping"
                },
                "arlen": {
                  "$ref": "#/$defs/extractAxiMapping"
                },
                "arlock": {
                  "$ref": "#/$defs/extractAxiMapping"
                },
                "arprot": {
                  "$ref": "#/$defs/extractAxiMapping"
                },
                "arqos": {
                  "$ref": "#/$defs/extractAxiMapping"
                },
                "arready": {
                  "$ref": "#/$defs/extractAxiMapping"
                },
                "arregion": {
                  "$ref": "#/$defs/extractAxiMapping"
                },
                "arsize": {
                  "$ref": "#/$defs/extractAxiMapping"
                },
                "aruser": {
                  "$ref": "#/$defs/extractAxiMapping"
                },
                "arvalid": {
                  "$ref": "#/$defs/extractAxiMapping"
                },
                "awaddr": {
                  "$ref": "#/$defs/extractAxiMapping"
                },
                "awburst": {
                  "$ref": "#/$defs/extractAxiMapping"
                },
                "awcache": {
                  "$ref": "#/$defs/extractAxiMapping"
                },
                "awid": {
                  "$ref": "#/$defs/extractAxiMapping"
                },
                "awlen": {
                  "$ref": "#/$defs/extractAxiMapping"
                },
                "awlock": {
                  "$ref": "#/$defs/extractAxiMapping"
                },
                "awprot": {
                  "$ref": "#/$defs/extractAxiMapping"
                },
                "awqos": {
                  "$ref": "#/$defs/extractAxiMapping"
                },
                "awready": {
                  "$ref": "#/$defs/extractAxiMapping"
                },
                "awregion": {
                  "$ref": "#/$defs/extractAxiMapping"
                },
                "awsize": {
                  "$ref": "#/$defs/extractAxiMapping"
                },
                "awuser": {
                  "$ref": "#/$defs/extractAxiMapping"
                },
                "awvalid": {
                  "$ref": "#/$defs/extractAxiMapping"
                },
                "bid": {
                  "$ref": "#/$defs/extractAxiMapping"
                },
                "bready": {
                  "$ref": "#/$defs/extractAxiMapping"
                },
                "bresp": {
                  "$ref": "#/$defs/extractAxiMapping"
                },
                "buser": {
                  "$ref": "#/$defs/extractAxiMapping"
                },
                "bvalid": {
                  "$ref": "#/$defs/extractAxiMapping"
                },
                "rdata": {
                  "$ref": "#/$defs/extractAxiMapping"
                },
                "rid": {
                  "$ref": "#/$defs/extractAxiMapping"
                },
                "rlast": {
                  "$ref": "#/$defs/extractAxiMapping"
                },
                "rready": {
                  "$ref": "#/$defs/extractAxiMapping"
                },
                "rresp": {
                  "$ref": "#/$defs/extractAxiMapping"
                },
                "ruser": {
                  "$ref": "#/$defs/extractAxiMapping"
                },
                "rvalid": {
                  "$ref": "#/$defs/extractAxiMapping"
                },
                "wdata": {
                  "$ref": "#/$defs/extractAxiMapping"
                },
                "wlast": {
                  "$ref": "#/$defs/extractAxiMapping"
                },
                "wready": {
                  "$ref": "#/$defs/extractAxiMapping"
                },
                "wstrb": {
                  "$ref": "#/$defs/extractAxiMapping"
                },
                "wuser": {
                  "$ref": "#/$defs/extractAxiMapping"
                },
                "wvalid": {
                  "$ref": "#/$defs/extractAxiMapping"
                }
              },
              "type": "object"
            },
            "name": {
              "description": "AXI port name supplied by CLI or source JSON.",
              "type": "string"
            },
            "profile": {
              "const": "axi4",
              "description": "AXI profile name used for standard signal mapping."
            },
            "transfers": {
              "description": "Extracted AXI ready/valid transfers in event order.",
              "items": {
                "$ref": "#/$defs/extractAxi4Transfer"
              },
              "type": "array"
            }
          },
          "required": [
            "name",
            "profile",
            "issue",
            "mappings",
            "transfers"
          ],
          "type": "object"
        },
        {
          "additionalProperties": true,
          "properties": {
            "issue": {
              "const": "H.c",
              "description": "Arm IHI 0022 issue used for this profile definition."
            },
            "mappings": {
              "additionalProperties": false,
              "description": "Resolved waveform mappings keyed by lowercase AXI standard signal name.",
              "properties": {
                "aclk": {
                  "$ref": "#/$defs/extractAxiMapping"
                },
                "araddr": {
                  "$ref": "#/$defs/extractAxiMapping"
                },
                "aresetn": {
                  "$ref": "#/$defs/extractAxiMapping"
                },
                "arprot": {
                  "$ref": "#/$defs/extractAxiMapping"
                },
                "arready": {
                  "$ref": "#/$defs/extractAxiMapping"
                },
                "arvalid": {
                  "$ref": "#/$defs/extractAxiMapping"
                },
                "awaddr": {
                  "$ref": "#/$defs/extractAxiMapping"
                },
                "awprot": {
                  "$ref": "#/$defs/extractAxiMapping"
                },
                "awready": {
                  "$ref": "#/$defs/extractAxiMapping"
                },
                "awvalid": {
                  "$ref": "#/$defs/extractAxiMapping"
                },
                "bready": {
                  "$ref": "#/$defs/extractAxiMapping"
                },
                "bresp": {
                  "$ref": "#/$defs/extractAxiMapping"
                },
                "bvalid": {
                  "$ref": "#/$defs/extractAxiMapping"
                },
                "rdata": {
                  "$ref": "#/$defs/extractAxiMapping"
                },
                "rready": {
                  "$ref": "#/$defs/extractAxiMapping"
                },
                "rresp": {
                  "$ref": "#/$defs/extractAxiMapping"
                },
                "rvalid": {
                  "$ref": "#/$defs/extractAxiMapping"
                },
                "wdata": {
                  "$ref": "#/$defs/extractAxiMapping"
                },
                "wready": {
                  "$ref": "#/$defs/extractAxiMapping"
                },
                "wstrb": {
                  "$ref": "#/$defs/extractAxiMapping"
                },
                "wvalid": {
                  "$ref": "#/$defs/extractAxiMapping"
                }
              },
              "type": "object"
            },
            "name": {
              "description": "AXI port name supplied by CLI or source JSON.",
              "type": "string"
            },
            "profile": {
              "const": "axi4-lite",
              "description": "AXI profile name used for standard signal mapping."
            },
            "transfers": {
              "description": "Extracted AXI ready/valid transfers in event order.",
              "items": {
                "$ref": "#/$defs/extractAxi4LiteTransfer"
              },
              "type": "array"
            }
          },
          "required": [
            "name",
            "profile",
            "issue",
            "mappings",
            "transfers"
          ],
          "type": "object"
        }
      ]
    },
    "extractAxiItemRecord": {
      "$ref": "#/$defs/itemRecordForExtractAxiTransfer"
    },
    "extractAxiMapping": {
      "additionalProperties": true,
      "properties": {
        "path": {
          "$ref": "#/$defs/canonicalPath",
          "description": "Canonical waveform signal path mapped to this AXI standard signal."
        }
      },
      "required": [
        "path"
      ],
      "type": "object"
    },
    "extractAxiTransfer": {
      "oneOf": [
        {
          "$ref": "#/$defs/extractAxi3Transfer"
        },
        {
          "$ref": "#/$defs/extractAxi4Transfer"
        },
        {
          "$ref": "#/$defs/extractAxi4LiteTransfer"
        }
      ]
    },
    "extractGenericItemRecord": {
      "$ref": "#/$defs/itemRecordForExtractGenericRow"
    },
    "extractGenericRow": {
      "additionalProperties": true,
      "properties": {
        "payload": {
          "description": "Ordered payload values sampled for this row.",
          "items": {
            "$ref": "#/$defs/extractPayloadValue"
          },
          "type": "array"
        },
        "sample_time": {
          "$ref": "#/$defs/normalizedTime",
          "description": "Pre-edge timestamp used to evaluate the predicate and sample payload values."
        },
        "source": {
          "description": "Source name supplied by CLI flags or source JSON.",
          "type": "string"
        },
        "time": {
          "$ref": "#/$defs/normalizedTime",
          "description": "Selected event timestamp emitted by extract generic."
        }
      },
      "required": [
        "time",
        "sample_time",
        "source",
        "payload"
      ],
      "type": "object"
    },
    "extractPayloadValue": {
      "additionalProperties": true,
      "properties": {
        "path": {
          "$ref": "#/$defs/canonicalPath",
          "description": "Canonical path of the sampled payload signal."
        },
        "value": {
          "$ref": "#/$defs/sampledValue",
          "description": "Sampled payload value formatted as a Verilog-style literal string."
        }
      },
      "required": [
        "path",
        "value"
      ],
      "type": "object"
    },
    "infoData": {
      "additionalProperties": true,
      "properties": {
        "time_end": {
          "$ref": "#/$defs/normalizedTime",
          "description": "Latest timestamp present in the waveform."
        },
        "time_start": {
          "$ref": "#/$defs/normalizedTime",
          "description": "Earliest timestamp present in the waveform."
        },
        "time_unit": {
          "description": "Dump time unit used to normalize timestamps in this waveform, for example 1ns.",
          "type": "string"
        }
      },
      "required": [
        "time_unit",
        "time_start",
        "time_end"
      ],
      "type": "object"
    },
    "infoItemRecord": {
      "$ref": "#/$defs/itemRecordForInfoData"
    },
    "itemRecord": {
      "oneOf": [
        {
          "$ref": "#/$defs/infoItemRecord"
        },
        {
          "$ref": "#/$defs/scopeItemRecord"
        },
        {
          "$ref": "#/$defs/signalItemRecord"
        },
        {
          "$ref": "#/$defs/valueItemRecord"
        },
        {
          "$ref": "#/$defs/changeItemRecord"
        },
        {
          "$ref": "#/$defs/propertyItemRecord"
        },
        {
          "$ref": "#/$defs/extractAxiItemRecord"
        },
        {
          "$ref": "#/$defs/extractGenericItemRecord"
        }
      ]
    },
    "itemRecordForChangeSnapshot": {
      "additionalProperties": true,
      "properties": {
        "command": {
          "const": "change"
        },
        "item": {
          "$ref": "#/$defs/changeSnapshot"
        },
        "seq": {
          "$ref": "#/$defs/sequence"
        },
        "type": {
          "const": "item"
        }
      },
      "required": [
        "type",
        "seq",
        "command",
        "item"
      ],
      "type": "object"
    },
    "itemRecordForExtractAxiTransfer": {
      "additionalProperties": true,
      "properties": {
        "command": {
          "const": "extract axi"
        },
        "item": {
          "$ref": "#/$defs/extractAxiTransfer"
        },
        "seq": {
          "$ref": "#/$defs/sequence"
        },
        "type": {
          "const": "item"
        }
      },
      "required": [
        "type",
        "seq",
        "command",
        "item"
      ],
      "type": "object"
    },
    "itemRecordForExtractGenericRow": {
      "additionalProperties": true,
      "properties": {
        "command": {
          "const": "extract generic"
        },
        "item": {
          "$ref": "#/$defs/extractGenericRow"
        },
        "seq": {
          "$ref": "#/$defs/sequence"
        },
        "type": {
          "const": "item"
        }
      },
      "required": [
        "type",
        "seq",
        "command",
        "item"
      ],
      "type": "object"
    },
    "itemRecordForInfoData": {
      "additionalProperties": true,
      "properties": {
        "command": {
          "const": "info"
        },
        "item": {
          "$ref": "#/$defs/infoData"
        },
        "seq": {
          "$ref": "#/$defs/sequence"
        },
        "type": {
          "const": "item"
        }
      },
      "required": [
        "type",
        "seq",
        "command",
        "item"
      ],
      "type": "object"
    },
    "itemRecordForPropertyRow": {
      "additionalProperties": true,
      "properties": {
        "command": {
          "const": "property"
        },
        "item": {
          "$ref": "#/$defs/propertyRow"
        },
        "seq": {
          "$ref": "#/$defs/sequence"
        },
        "type": {
          "const": "item"
        }
      },
      "required": [
        "type",
        "seq",
        "command",
        "item"
      ],
      "type": "object"
    },
    "itemRecordForScopeEntry": {
      "additionalProperties": true,
      "properties": {
        "command": {
          "const": "scope"
        },
        "item": {
          "$ref": "#/$defs/scopeEntry"
        },
        "seq": {
          "$ref": "#/$defs/sequence"
        },
        "type": {
          "const": "item"
        }
      },
      "required": [
        "type",
        "seq",
        "command",
        "item"
      ],
      "type": "object"
    },
    "itemRecordForSignalEntry": {
      "additionalProperties": true,
      "properties": {
        "command": {
          "const": "signal"
        },
        "item": {
          "$ref": "#/$defs/signalEntry"
        },
        "seq": {
          "$ref": "#/$defs/sequence"
        },
        "type": {
          "const": "item"
        }
      },
      "required": [
        "type",
        "seq",
        "command",
        "item"
      ],
      "type": "object"
    },
    "itemRecordForValueSnapshot": {
      "additionalProperties": true,
      "properties": {
        "command": {
          "const": "value"
        },
        "item": {
          "$ref": "#/$defs/valueSnapshot"
        },
        "seq": {
          "$ref": "#/$defs/sequence"
        },
        "type": {
          "const": "item"
        }
      },
      "required": [
        "type",
        "seq",
        "command",
        "item"
      ],
      "type": "object"
    },
    "normalizedTime": {
      "description": "Normalized timestamp rendered in the dump's time unit, for example 10ns.",
      "type": "string"
    },
    "propertyItemRecord": {
      "$ref": "#/$defs/itemRecordForPropertyRow"
    },
    "propertyRow": {
      "additionalProperties": true,
      "properties": {
        "kind": {
          "description": "Property result kind captured for this row.",
          "enum": [
            "match",
            "assert",
            "deassert"
          ],
          "type": "string"
        },
        "sample_time": {
          "$ref": "#/$defs/normalizedTime",
          "description": "Timestamp used to evaluate the property expression."
        },
        "time": {
          "$ref": "#/$defs/normalizedTime",
          "description": "Trigger timestamp emitted by the property command."
        }
      },
      "required": [
        "time",
        "sample_time",
        "kind"
      ],
      "type": "object"
    },
    "sampledSignalValue": {
      "additionalProperties": true,
      "properties": {
        "path": {
          "$ref": "#/$defs/canonicalPath",
          "description": "Canonical path of the sampled signal."
        },
        "value": {
          "$ref": "#/$defs/sampledValue",
          "description": "Sampled value for this signal in the selected timestamp snapshot."
        }
      },
      "required": [
        "path",
        "value"
      ],
      "type": "object"
    },
    "sampledValue": {
      "description": "Stable sampled signal value formatted as a Verilog-style literal string.",
      "type": "string"
    },
    "scopeEntry": {
      "additionalProperties": true,
      "properties": {
        "depth": {
          "description": "Zero-based scope depth from the dump root used by list and tree renderers.",
          "minimum": 0,
          "type": "integer"
        },
        "kind": {
          "$ref": "#/$defs/scopeKind",
          "description": "Stable scope kind alias for this scope entry."
        },
        "path": {
          "$ref": "#/$defs/canonicalPath",
          "description": "Canonical hierarchy path for this scope entry."
        }
      },
      "required": [
        "path",
        "depth",
        "kind"
      ],
      "type": "object"
    },
    "scopeItemRecord": {
      "$ref": "#/$defs/itemRecordForScopeEntry"
    },
    "scopeKind": {
      "description": "Stable scope kind alias emitted by wavepeek for the selected scope.",
      "enum": [
        "module",
        "task",
        "function",
        "begin",
        "fork",
        "generate",
        "struct",
        "union",
        "class",
        "interface",
        "package",
        "program",
        "unknown"
      ],
      "type": "string"
    },
    "sequence": {
      "minimum": 0,
      "type": "integer"
    },
    "signalEntry": {
      "additionalProperties": true,
      "properties": {
        "kind": {
          "$ref": "#/$defs/signalKind",
          "description": "Stable signal kind alias for this signal entry."
        },
        "name": {
          "description": "Signal name as declared inside its immediate parent scope.",
          "type": "string"
        },
        "path": {
          "$ref": "#/$defs/canonicalPath",
          "description": "Canonical hierarchy path for this signal entry."
        },
        "width": {
          "description": "Declared packed bit width when the waveform backend reports one.",
          "minimum": 1,
          "type": "integer"
        }
      },
      "required": [
        "name",
        "path",
        "kind"
      ],
      "type": "object"
    },
    "signalItemRecord": {
      "$ref": "#/$defs/itemRecordForSignalEntry"
    },
    "signalKind": {
      "description": "Stable signal kind alias emitted by wavepeek for the selected signal.",
      "enum": [
        "event",
        "integer",
        "parameter",
        "real",
        "reg",
        "supply0",
        "supply1",
        "time",
        "tri",
        "triand",
        "trior",
        "trireg",
        "tri0",
        "tri1",
        "wand",
        "wire",
        "wor",
        "string",
        "port",
        "sparse_array",
        "real_time",
        "real_parameter",
        "bit",
        "logic",
        "int",
        "short_int",
        "long_int",
        "byte",
        "enum",
        "short_real",
        "boolean",
        "bit_vector"
      ],
      "type": "string"
    },
    "streamCommand": {
      "enum": [
        "info",
        "scope",
        "signal",
        "value",
        "change",
        "property",
        "extract axi",
        "extract generic"
      ],
      "type": "string"
    },
    "streamContextData": {
      "anyOf": [
        {
          "$ref": "#/$defs/extractAxiContext"
        }
      ]
    },
    "streamSummary": {
      "additionalProperties": true,
      "properties": {
        "diagnostics": {
          "minimum": 0,
          "type": "integer"
        },
        "items": {
          "minimum": 0,
          "type": "integer"
        },
        "status": {
          "const": "ok"
        },
        "truncated": {
          "type": "boolean"
        }
      },
      "required": [
        "status",
        "items",
        "diagnostics",
        "truncated"
      ],
      "type": "object"
    },
    "valueItemRecord": {
      "$ref": "#/$defs/itemRecordForValueSnapshot"
    },
    "valueSnapshot": {
      "additionalProperties": true,
      "properties": {
        "signals": {
          "description": "Signal values sampled at this timestamp.",
          "items": {
            "$ref": "#/$defs/sampledSignalValue"
          },
          "type": "array"
        },
        "time": {
          "$ref": "#/$defs/normalizedTime",
          "description": "Timestamp requested by the value command."
        }
      },
      "required": [
        "time",
        "signals"
      ],
      "type": "object"
    }
  },
  "$id": "https://kleverhq.github.io/wavepeek/schema-stream-v2.2.json",
  "$schema": "https://json-schema.org/draft/2020-12/schema",
  "description": "Canonical schema for one wavepeek --jsonl stream record. Validate each JSONL line independently; stream order and summary counts are stateful invariants.",
  "oneOf": [
    {
      "$ref": "#/$defs/beginRecord"
    },
    {
      "$ref": "#/$defs/itemRecord"
    },
    {
      "$ref": "#/$defs/diagnosticRecord"
    },
    {
      "$ref": "#/$defs/endRecord"
    }
  ],
  "title": "wavepeek JSONL stream record"
}
